README
setup.py
gen_rst_readme/__init__.py
gen_rst_readme/gen_rst_readme.py
gen_rst_readme.egg-info/PKG-INFO
gen_rst_readme.egg-info/SOURCES.txt
gen_rst_readme.egg-info/dependency_links.txt
gen_rst_readme.egg-info/entry_points.txt
gen_rst_readme.egg-info/requires.txt
gen_rst_readme.egg-info/top_level.txt