Metadata-Version: 1.0
Name: gen-rst-readme
Version: 0.0.1
Summary: Generates a rst readme from a md readme.
Home-page: https://github.com/christophersu/gen_rst_readme
Author: Christopher Su
Author-email: gh@christopher.su
License: UNKNOWN
Platform: UNKNOWN
